tap_healthie/__init__.py
tap_healthie/client.py
tap_healthie/schemas/appointment_types.json
tap_healthie/schemas/users.json
tap_healthie/streams.py
tap_healthie/tap.py
fort_health_tap_healthie-0.0.1.dist-info/entry_points.txt
fort_health_tap_healthie-0.0.1.dist-info/METADATA
fort_health_tap_healthie-0.0.1.dist-info/WHEEL
fort_health_tap_healthie-0.0.1.dist-info/RECORD
