Metadata-Version: 2.1
Name: fort-health-tap-healthie
Version: 0.0.1
Summary: `tap-healthie` is a Singer tap for Healthie, built with the Meltano Singer SDK.
License: Apache 2.0
Keywords: ELT,Healthie
Author: Kevin Kong
Requires-Python: >=3.7.1,<3.12
Classifier: License :: Other/Proprietary License
Classifier: Programming Language :: Python :: 3
Classifier: Programming Language :: Python :: 3.8
Classifier: Programming Language :: Python :: 3.9
Classifier: Programming Language :: Python :: 3.10
Classifier: Programming Language :: Python :: 3.11
Provides-Extra: s3
Requires-Dist: fs-s3fs (>=1.1.1,<2.0.0) ; extra == "s3"
Requires-Dist: requests (>=2.28.2,<3.0.0)
Requires-Dist: singer-sdk (>=0.26.0,<0.27.0)
